setup.cfg
setup.py
egoreliseev_python_hw1/__init__.py
egoreliseev_python_hw1/main.py
egoreliseev_python_hw1.egg-info/PKG-INFO
egoreliseev_python_hw1.egg-info/SOURCES.txt
egoreliseev_python_hw1.egg-info/dependency_links.txt
egoreliseev_python_hw1.egg-info/not-zip-safe
egoreliseev_python_hw1.egg-info/top_level.txt