Metadata-Version: 1.0
Name: egoreliseev-python-hw1
Version: 0.0
Summary: Build AST for fibonacci func
Home-page: UNKNOWN
Author: UNKNOWN
Author-email: eliseevegor1920@gmail.com
License: UNKNOWN
Platform: UNKNOWN
